karrio/mappers/canadapost/__init__.py
karrio/mappers/canadapost/mapper.py
karrio/mappers/canadapost/proxy.py
karrio/mappers/canadapost/settings.py
karrio/providers/canadapost/__init__.py
karrio/providers/canadapost/error.py
karrio/providers/canadapost/rate.py
karrio/providers/canadapost/tracking.py
karrio/providers/canadapost/units.py
karrio/providers/canadapost/utils.py
karrio/providers/canadapost/pickup/__init__.py
karrio/providers/canadapost/pickup/cancel.py
karrio/providers/canadapost/pickup/create.py
karrio/providers/canadapost/pickup/update.py
karrio/providers/canadapost/shipment/__init__.py
karrio/providers/canadapost/shipment/cancel.py
karrio/providers/canadapost/shipment/contract.py
karrio/providers/canadapost/shipment/create.py
karrio/providers/canadapost/shipment/non_contract.py
karrio.canadpost-2022.8.11.dist-info/METADATA
karrio.canadpost-2022.8.11.dist-info/WHEEL
karrio.canadpost-2022.8.11.dist-info/top_level.txt
karrio.canadpost-2022.8.11.dist-info/RECORD
