Metadata-Version: 2.1
Name: karrio.canadpost
Version: 2022.8.11
Summary: Karrio - Canada Post Shipping Extension
Home-page: https://github.com/karrioapi/karrio
Author: karrio
Author-email: hello@karrio.io
License: Apache-2.0
Platform: UNKNOWN
Classifier: Intended Audience :: Developers
Classifier: Operating System :: OS Independent
Classifier: Programming Language :: Python :: 3
Classifier: License :: OSI Approved :: Apache Software License
Requires-Dist: carrier.canadapost
Requires-Dist: karrio
